{
"type": "FeatureCollection",
"crs": { "type": "name", "properties": { "name": "urn:ogc:def:crs:OGC:1.3:CRS84" } },
"features": [
{ "type": "Feature", "properties": { "Race": "Start" }, "geometry": { "type": "Point", "coordinates": [ -77.497816800021923, 39.564955578934843 ] } },
{ "type": "Feature", "properties": { "Race": "Finish" }, "geometry": { "type": "Point", "coordinates": [ -77.473247793659638, 39.490043862587747 ] } }
]
}
